MANIFEST.in
README.md
setup.py
chlkt/__init__.py
chlkt/chalk-it-icon.ico
chlkt/chalkit_python_api-0.0.5-py3-none-any.whl
chlkt/dashboard.5d35396aa772fa7dcc69.js
chlkt/dashboard.fe6e47a8f3cf5aa506c5.css
chlkt/editor.5e9a73a078f824f83867.js
chlkt/editor.e59e5684261578de2de2.css
chlkt/index-view.html
chlkt/index.html
chlkt/main.py
chlkt/pyodide.worker.20975526207d34447b0d.js
chlkt/Templates/Images/advanced-kpi-js.png
chlkt/Templates/Images/advanced-kpi-py.png
chlkt/Templates/Images/bar-chart.png
chlkt/Templates/Images/base64-image-js.png
chlkt/Templates/Images/base64-image-py.png
chlkt/Templates/Images/bubble-chart-js.png
chlkt/Templates/Images/buttons-py.png
chlkt/Templates/Images/clock-and-delay.png
chlkt/Templates/Images/combo-box-js.png
chlkt/Templates/Images/combo-box-py.png
chlkt/Templates/Images/csv-array.png
chlkt/Templates/Images/csv-player.png
chlkt/Templates/Images/csv-read-write-js.png
chlkt/Templates/Images/date-picker.png
chlkt/Templates/Images/echarts-covid-comparison-js.png
chlkt/Templates/Images/editable-table-2D.png
chlkt/Templates/Images/formula-js.png
chlkt/Templates/Images/formula-py.png
chlkt/Templates/Images/generic-html-js.png
chlkt/Templates/Images/generic-html-py.png
chlkt/Templates/Images/json-to-table-columnwise-js.png
chlkt/Templates/Images/json-to-table-linewise-js.png
chlkt/Templates/Images/line-chart.png
chlkt/Templates/Images/list-js.png
chlkt/Templates/Images/list-py.png
chlkt/Templates/Images/live-demo-js.png
chlkt/Templates/Images/live-demo-py.png
chlkt/Templates/Images/markdown-js.png
chlkt/Templates/Images/markdown-py.png
chlkt/Templates/Images/matplotlib-bar-color-py.png
chlkt/Templates/Images/matplotlib-bar-py.png
chlkt/Templates/Images/multi-select-js.png
chlkt/Templates/Images/multi-select-py.png
chlkt/Templates/Images/osm-basic-geojson.png
chlkt/Templates/Images/osm-choropleth-js.png
chlkt/Templates/Images/osm-choropleth-py.png
chlkt/Templates/Images/osm-drawing-features.png
chlkt/Templates/Images/osm-geojson-line.png
py_chalk_it.egg-info/PKG-INFO
py_chalk_it.egg-info/SOURCES.txt
py_chalk_it.egg-info/dependency_links.txt
py_chalk_it.egg-info/entry_points.txt
py_chalk_it.egg-info/requires.txt
py_chalk_it.egg-info/top_level.txt